sumocr/__init__.py
sumocr/helpers.py
sumocr/interactive_scenarios/__init__.py
sumocr/interactive_scenarios/simulations.py
sumocr/interactive_scenarios/utility.py
sumocr/interface/__init__.py
sumocr/interface/ego_vehicle.py
sumocr/interface/id_mapper.py
sumocr/interface/interfaces/__init__.py
sumocr/interface/interfaces/base_interface.py
sumocr/interface/interfaces/dynamic_obstacle_interface.py
sumocr/interface/interfaces/pedestrian_interface.py
sumocr/interface/interfaces/traffic_light_interface.py
sumocr/interface/interfaces/vehicle_interface.py
sumocr/interface/params.py
sumocr/interface/sumo_simulation.py
sumocr/interface/sumo_simulation_backend.py
sumocr/interface/sumo_simulation_interface.py
sumocr/interface/util.py
sumocr/scenario/__init__.py
sumocr/scenario/abstract_scenario_wrapper.py
sumocr/scenario/scenario_wrapper.py
sumocr/sumo_config/.sumo.cfg
sumocr/sumo_config/__init__.py
sumocr/sumo_config/default.py
sumocr/sumo_config/pathConfig.py
sumocr/sumo_config/plot_params.py
sumocr/sumo_docker/__init__.py
sumocr/sumo_docker/interface/__init__.py
sumocr/sumo_docker/interface/docker_interface.py
sumocr/sumo_docker/rpc/__init__.py
sumocr/sumo_docker/rpc/messaging.py
sumocr/sumo_docker/rpc/server.crt
sumocr/sumo_docker/rpc/sumo_client.py
sumocr/sumo_docker/utils/__init__.py
sumocr/sumo_docker/utils/docker_runner.py
sumocr/visualization/__init__.py
sumocr/visualization/video.py
sumocr-2024.1.dist-info/LICENSE.txt
sumocr-2024.1.dist-info/METADATA
sumocr-2024.1.dist-info/WHEEL
sumocr-2024.1.dist-info/RECORD
