Metadata-Version: 2.1
Name: sumocr
Version: 2024.1
Summary: Python tool to interface with the SUMO traffic simulator
License: BSD License
Author: Florian Finkeldei
Author-email: florian.finkeldei@tum.de
Requires-Python: >=3.8,<4.0
Classifier: License :: Other/Proprietary License
Classifier: Programming Language :: Python :: 3
Classifier: Programming Language :: Python :: 3.8
Classifier: Programming Language :: Python :: 3.9
Classifier: Programming Language :: Python :: 3.10
Classifier: Programming Language :: Python :: 3.11
Classifier: Programming Language :: Python :: 3.12
Requires-Dist: Pillow (>=10.0.1,<11.0.0)
Requires-Dist: commonroad-io (>=2024.1,<2025.0)
Requires-Dist: docker (>=6.1,<7.0)
Requires-Dist: ffmpeg (>=1.4,<2.0)
Requires-Dist: grpcio (>=1.27,<2.0)
Requires-Dist: ipython (>=8.8,<9.0)
Requires-Dist: libsumo (>=1.19.0,<2.0.0)
Requires-Dist: lxml (>=4.2.2,<5.0.0)
Requires-Dist: matplotlib (>=3.0.0,<4.0.0)
Requires-Dist: numpy (>=1.22,<2.0) ; python_version == "3.8"
Requires-Dist: numpy (>=1.26,<2.0) ; python_version >= "3.9" and python_version < "4.0"
Requires-Dist: packaging (>=23.2,<24.0)
Requires-Dist: shapely (>=2.0.0,<3.0.0)
Requires-Dist: traci (>=1.19.0,<2.0.0)
